setup.cfg
setup.py
behave_logger/__init__.py
behave_logger/logger.py
behave_logger.egg-info/PKG-INFO
behave_logger.egg-info/SOURCES.txt
behave_logger.egg-info/dependency_links.txt
behave_logger.egg-info/top_level.txt