Metadata-Version: 1.1
Name: behave-logger
Version: 1.0.0
Summary: A specific logger util for Behave
Home-page: https://github.com/borbamartin/behave-logger
Author: Martin Borba
Author-email: borbamartin@gmail.com
License: UNKNOWN
Download-URL: https://github.com/borbamartin/behave-logger/tarball/1.0.0
Keywords: testing,logging,behave,python
Platform: UNKNOWN
